<?xml version="1.0" ?>
<annotation>
   
	
   <folder>hammer</folder>
   
	
   <filename>img1353.jpg</filename>
   
	
   <path>/Users/divyansh/Programming/dataset/train/hammer/img1353.jpg</path>
   
	
   <source>
      
		
      <database>Unknown</database>
      
	
   </source>
   
	
   <size>
      
		
      <width>360</width>
      
		
      <height>480</height>
      
		
      <depth>3</depth>
      
	
   </size>
   
	
   <segmented>0</segmented>
   
	
   <object>
      
		
      <name>hammer</name>
      
		
      <pose>Unspecified</pose>
      
		
      <truncated>0</truncated>
      
		
      <difficult>0</difficult>
      
		
      <bndbox>
         
			
         <xmin>246</xmin>
         
			
         <ymin>435</ymin>
         
			
         <xmax>109</xmax>
         
			
         <ymax>87</ymax>
         
		
      </bndbox>
      
	
   </object>
   

</annotation>
