<?xml version="1.0" ?>
<annotation>
   
	
   <folder>hammer</folder>
   
	
   <filename>img1345.jpg</filename>
   
	
   <path>/Users/utkarsh/dev/fyp/dataset/train/hammer/img1345.jpg</path>
   
	
   <source>
      
		
      <database>Unknown</database>
      
	
   </source>
   
	
   <size>
      
		
      <width>500</width>
      
		
      <height>375</height>
      
		
      <depth>3</depth>
      
	
   </size>
   
	
   <segmented>0</segmented>
   
	
   <object>
      
		
      <name>hammer</name>
      
		
      <pose>Unspecified</pose>
      
		
      <truncated>0</truncated>
      
		
      <difficult>0</difficult>
      
		
      <bndbox>
         
			
         <xmin>486</xmin>
         
			
         <ymin>375</ymin>
         
			
         <xmax>10</xmax>
         
			
         <ymax>71</ymax>
         
		
      </bndbox>
      
	
   </object>
   

</annotation>
