<annotation>
	<folder>custom hammer dataset</folder>
	<filename>0013.jpg</filename>
	<path>/Users/divyansh/Programming/dataset/custom hammer dataset/0013.jpg</path>
	<source>
		<database>Unknown</database>
	</source>
	<size>
		<width>640</width>
		<height>352</height>
		<depth>3</depth>
	</size>
	<segmented>0</segmented>
	<object>
		<name>hammer</name>
		<pose>Unspecified</pose>
		<truncated>1</truncated>
		<difficult>0</difficult>
		<bndbox>
			<xmin>109</xmin>
			<ymin>73</ymin>
			<xmax>640</xmax>
			<ymax>245</ymax>
		</bndbox>
	</object>
</annotation>
